README.md
setup.py
hgtiles/__init__.py
hgtiles/bed2ddb.py
hgtiles/bedarcsdb.py
hgtiles/beddb.py
hgtiles/bedfile.py
hgtiles/bigwig.py
hgtiles/chromsizes.py
hgtiles/cooler.py
hgtiles/density.py
hgtiles/files.py
hgtiles/format.py
hgtiles/geo.py
hgtiles/hitile.py
hgtiles/imtiles.py
hgtiles/multivec.py
hgtiles/npmatrix.py
hgtiles/npvector.py
hgtiles/points.py
hgtiles/time_interval.py
hgtiles/utils.py
hgtiles.egg-info/PKG-INFO
hgtiles.egg-info/SOURCES.txt
hgtiles.egg-info/dependency_links.txt
hgtiles.egg-info/requires.txt
hgtiles.egg-info/top_level.txt