Metadata-Version: 1.0
Name: hgtiles
Version: 0.2.17
Summary: Tile loading for higlass-server
Home-page: UNKNOWN
Author: Peter Kerpedjiev
Author-email: pkerpedjiev@gmail.com
License: UNKNOWN
Platform: UNKNOWN
